fipiran/__init__.py
fipiran/funds.py
fipiran/symbols.py
fipiran-1.0.2.dist-info/WHEEL
fipiran-1.0.2.dist-info/METADATA
fipiran-1.0.2.dist-info/RECORD
