Metadata-Version: 2.3
Name: fipiran
Version: 1.0.2
Summary: a library to retrieve data from fipiran.ir website
Keywords: fipiran,client
License: GNU General Public License v3 (GPLv3)
Classifier: License :: OSI Approved :: GNU General Public License v3 (GPLv3)
Classifier: Programming Language :: Python :: 3.10
Requires-Dist: aiohutils>=0.21.0
Requires-Dist: jdatetime
Requires-Dist: lxml
Requires-Dist: pandas[pyarrow]>=2.2.1
Requires-Dist: pydantic
Requires-Python: >=3.13
Project-URL: Homepage, https://github.com/5j9/fipiran
